Sample_adder/sample_adder.sv
module full_add ( a , b , cin , sum );
    input a, b , cin;
    output sum;

    assign sum = a + b + cin; 
    
endmodule

Sample_adder/sample_tb_adder.sv
// Code your testbench here
module add_tb;
  reg a,b,cin;
  wire sum;
 
// instantiate the DUT block  
  full_add f1(.a(a),.b(b),.cin(cin),.sum(sum));
 
// this particular line is added to dump the file on online simulator
  initial begin $dumpfile("full_tb.vcd");$dumpvars(); end

// insert all the inputs 
  initial begin a=1'b1;  #4; a=1'b0;#10 $stop();end
  initial begin b=1'b1; forever #2 b=~b;end
  initial begin cin=1'b1;forever #1 cin=~cin; #10 $stop();end

// monitor all the input and output ports at times 
// when any of the input changes its state

 initial begin $monitor("A=%b, B=%b, Cin=%b, Sum=%b",a,b,cin,sum);end
 endmodule

Sample_adder/full_tb.vcd
$date
	Sun Apr 09 13:21:37 2023
$end
$version
	Icarus Verilog
$end
$timescale
	1s
$end
$scope module add_tb $end
$var wire 1 ! sum $end
$var reg 1 " a $end
$var reg 1 # b $end
$var reg 1 $ cin $end
$scope module f1 $end
$var wire 1 " a $end
$var wire 1 # b $end
$var wire 1 $ cin $end
$var wire 1 ! sum $end
$upscope $end
$upscope $end
$enddefinitions $end
$comment Show the parameter values. $end
$dumpall
$end
#0
$dumpvars
1$
1#
1"
1!
$end
#1
0!
0$
#2
1$
0!
0#
#3
1!
0$
#4
1$
1#
0!
0"
#5
1!
0$
#6
1$
1!
0#
#7
0!
0$
#8
1$
0!
1#
#9
1!
0$
#10
1$
1!
0#
#11
0!
0$
#12
1$
0!
1#
#13
1!
0$
